hbrl/__init__.py
hbrl/brouillon.py
hbrl/agents/__init__.py
hbrl/agents/agent.py
hbrl/agents/agents_index.py
hbrl/agents/value_based_agent.py
hbrl/agents/continuous/__init__.py
hbrl/agents/continuous/ddpg.py
hbrl/agents/continuous/distributional_ddpg.py
hbrl/agents/continuous/sac.py
hbrl/agents/discrete/__init__.py
hbrl/agents/discrete/distributional_dqn.py
hbrl/agents/discrete/dqn.py
hbrl/agents/global_planning/__init__.py
hbrl/agents/global_planning/reachability_graph_learning/__init__.py
hbrl/agents/global_planning/reachability_graph_learning/rgl.py
hbrl/agents/global_planning/reachability_graph_learning/sgm.py
hbrl/agents/global_planning/reachability_graph_learning/sorb.py
hbrl/agents/global_planning/sub_goal_generation_learning/__init__.py
hbrl/agents/global_planning/sub_goal_generation_learning/hrl.py
hbrl/agents/goal_conditioned_wrappers/__init__.py
hbrl/agents/goal_conditioned_wrappers/goal_conditioned_agent.py
hbrl/agents/goal_conditioned_wrappers/goal_conditioned_value_based_agent.py
hbrl/agents/goal_conditioned_wrappers/her.py
hbrl/agents/goal_conditioned_wrappers/tilo.py
hbrl/agents/utils/__init__.py
hbrl/agents/utils/functions.py
hbrl/agents/utils/mlp.py
hbrl/agents/utils/replay_buffer.py
hbrl/environments/__init__.py
hbrl/environments/environment.py
hbrl/environments/environments_index.py
hbrl/environments/goal_reaching_environment.py
hbrl/environments/ant_maze/__init__.py
hbrl/environments/ant_maze/ant_maze.py
hbrl/environments/ant_maze/mujoco_model_utils.py
hbrl/environments/ant_maze/mujoco_files/__init__.py
hbrl/environments/ant_maze/mujoco_files/xml_generator.py
hbrl/environments/ant_maze/mujoco_files/common/__init__.py
hbrl/environments/ant_maze/mujoco_files/maps_txt/__init__.py
hbrl/environments/ant_maze/mujoco_files/maps_txt/csv_converter.py
hbrl/environments/grid_world/__init__.py
hbrl/environments/grid_world/discrete_grid_world.py
hbrl/environments/grid_world/goal_conditioned_discrete_grid_world.py
hbrl-0.0.22.dist-info/LICENCE
hbrl-0.0.22.dist-info/METADATA
hbrl-0.0.22.dist-info/WHEEL
hbrl-0.0.22.dist-info/top_level.txt
hbrl-0.0.22.dist-info/RECORD
